mlseo/__init__.py
mlseo/_nbdev.py
mlseo/core.py
mlseo/example.py
mlseo/pip_upgrades.py
mlseo-0.0.22.dist-info/LICENSE
mlseo-0.0.22.dist-info/METADATA
mlseo-0.0.22.dist-info/WHEEL
mlseo-0.0.22.dist-info/top_level.txt
mlseo-0.0.22.dist-info/RECORD
